[
  {
    "rank": 1,
    "name": "Marc Schnatterer",
    "full_name": "Unknown",
    "appearances": 461,
    "goals": 124,
    "assists": 128,
    "minutes_played": 35073,
    "period": "2008-2021",
    "jersey_name": "Schnatterer",
    "jersey_number": "Unknown",
    "yellow_cards": 42,
    "red_cards": 0,
    "club": "1.FC Heidenheim 1846",
    "position": "Attack - Left Winger",
    "height": "1,80 m",
    "nation": "Germany",
    "nation_code": "de",
    "profile_url": "https://www.transfermarkt.us/marc-schnatterer/profil/spieler/18684",
    "image_url": "https://img.a.transfermarkt.technology/portrait/big/18684-1657204787.jpg?lm=1",
    "club_logo_url": null,
    "date_of_birth": "18.11.1985",
    "place_of_birth": "Heilbronn",
    "status": "Retired"
  },
  {
    "rank": 2,
    "name": "Tim Kleindienst",
    "full_name": "Unknown",
    "appearances": 172,
    "goals": 83,
    "assists": 23,
    "minutes_played": 14491,
    "period": "16/17-19/24",
    "jersey_name": "Kleindienst",
    "jersey_number": "19",
    "yellow_cards": 38,
    "red_cards": 0,
    "club": "1.FC Heidenheim 1846",
    "position": "Attack - Centre-Forward",
    "height": "1,94 m",
    "nation": "Germany",
    "nation_code": "de",
    "profile_url": "https://www.transfermarkt.us/tim-kleindienst/profil/spieler/193033",
    "image_url": "https://img.a.transfermarkt.technology/portrait/big/193033-1722945738.jpg?lm=1",
    "club_logo_url": null,
    "date_of_birth": "31.08.1995",
    "place_of_birth": "Jüterbog",
    "status": "Borussia Mönchengladbach"
  },
  {
    "rank": 3,
    "name": "Andreas Spann",
    "full_name": "Unknown",
    "appearances": 141,
    "goals": 43,
    "assists": 22,
    "minutes_played": 10957,
    "period": "2007-2013",
    "jersey_name": "Spann",
    "jersey_number": "-",
    "yellow_cards": 23,
    "red_cards": 0,
    "club": "1.FC Heidenheim 1846",
    "position": "Attack - Centre-Forward",
    "height": "1,83 m",
    "nation": "Germany",
    "nation_code": "de",
    "profile_url": "https://www.transfermarkt.us/andreas-spann/profil/spieler/3969",
    "image_url": "https://img.a.transfermarkt.technology/portrait/big/s_3969_2036_2010_2.jpg?lm=1",
    "club_logo_url": null,
    "date_of_birth": "17.05.1984",
    "place_of_birth": "Ulm",
    "status": "Retired"
  },
  {
    "rank": 4,
    "name": "Patrick Mayer",
    "full_name": "Unknown",
    "appearances": 111,
    "goals": 42,
    "assists": 17,
    "minutes_played": 6814,
    "period": "09/11-12/15",
    "jersey_name": "Mayer",
    "jersey_number": "Unknown",
    "yellow_cards": 10,
    "red_cards": 0,
    "club": "1.FC Heidenheim 1846",
    "position": "Attack - Centre-Forward",
    "height": "1,80 m",
    "nation": "Germany",
    "nation_code": "de",
    "profile_url": "https://www.transfermarkt.us/patrick-mayer/profil/spieler/47942",
    "image_url": "https://img.a.transfermarkt.technology/portrait/big/47942-1468420197.jpg?lm=1",
    "club_logo_url": null,
    "date_of_birth": "28.03.1988",
    "place_of_birth": "Wangen im Allgäu",
    "status": "Retired"
  },
  {
    "rank": 5,
    "name": "Alexander Raaf",
    "full_name": "Unknown",
    "appearances": 118,
    "goals": 41,
    "assists": 0,
    "minutes_played": 7637,
    "period": "2003-2008",
    "jersey_name": "Raaf",
    "jersey_number": "Unknown",
    "yellow_cards": 15,
    "red_cards": 1,
    "club": "1.FC Heidenheim 1846",
    "position": "Attack - Centre-Forward",
    "height": "1,82 m",
    "nation": "Germany",
    "nation_code": "de",
    "profile_url": "https://www.transfermarkt.us/alexander-raaf/profil/spieler/24755",
    "image_url": "https://img.a.transfermarkt.technology/portrait/big/E_I_s_24755_75_2009_1.jpg?lm=1",
    "club_logo_url": null,
    "date_of_birth": "21.01.1974",
    "place_of_birth": "Unknown",
    "status": "Retired"
  },
  {
    "rank": 6,
    "name": "Dinko Radojevic",
    "full_name": "Unknown",
    "appearances": 88,
    "goals": 41,
    "assists": 0,
    "minutes_played": 7532,
    "period": "2002-2007",
    "jersey_name": "Radojevic",
    "jersey_number": "Unknown",
    "yellow_cards": 13,
    "red_cards": 0,
    "club": "1.FC Heidenheim 1846",
    "position": "Midfield - Attacking Midfield",
    "height": "1,79 m",
    "nation": "Croatia",
    "nation_code": "hr",
    "profile_url": "https://www.transfermarkt.us/dinko-radojevic/profil/spieler/24757",
    "image_url": "https://sv-ebersbach.de/wp-content/uploads/2024/01/1920xauto-2-1638x2048.webp",
    "club_logo_url": null,
    "date_of_birth": "17.08.1978",
    "place_of_birth": "Nova Gradiska",
    "status": "Retired"
  },
  {
    "rank": 7,
    "name": "Dieter Jarosch",
    "full_name": "Unknown",
    "appearances": 116,
    "goals": 40,
    "assists": 2,
    "minutes_played": 6576,
    "period": "2007-2012",
    "jersey_name": "Jarosch",
    "jersey_number": "Unknown",
    "yellow_cards": 14,
    "red_cards": 1,
    "club": "1.FC Heidenheim 1846",
    "position": "Attack - Centre-Forward",
    "height": "1,87 m",
    "nation": "Germany",
    "nation_code": "de",
    "profile_url": "https://www.transfermarkt.us/dieter-jarosch/profil/spieler/12240",
    "image_url": "https://img.a.transfermarkt.technology/portrait/big/s_12240_2036_2010_2.jpg?lm=1",
    "club_logo_url": null,
    "date_of_birth": "14.09.1980",
    "place_of_birth": "Freiburg im Breisgau",
    "status": "Retired"
  },
  {
    "rank": 8,
    "name": "Tim Göhlert",
    "full_name": "Unknown",
    "appearances": 310,
    "goals": 37,
    "assists": 8,
    "minutes_played": 26166,
    "period": "2005-2016",
    "jersey_name": "Göhlert",
    "jersey_number": "Unknown",
    "yellow_cards": 63,
    "red_cards": 2,
    "club": "1.FC Heidenheim 1846",
    "position": "Defender - Centre-Back",
    "height": "1,90 m",
    "nation": "Germany",
    "nation_code": "de",
    "profile_url": "https://www.transfermarkt.us/tim-gohlert/profil/spieler/18077",
    "image_url": "https://img.a.transfermarkt.technology/portrait/big/18077-1512926195.jpg?lm=1",
    "club_logo_url": null,
    "date_of_birth": "15.09.1984",
    "place_of_birth": "Karl-Marx-Stadt",
    "status": "TSG Söflingen"
  },
  {
    "rank": 9,
    "name": "Robert Leipertz",
    "full_name": "Unknown",
    "appearances": 167,
    "goals": 37,
    "assists": 26,
    "minutes_played": 10953,
    "period": "14/16-19/22",
    "jersey_name": "Leipertz",
    "jersey_number": "Unknown",
    "yellow_cards": 13,
    "red_cards": 0,
    "club": "1.FC Heidenheim 1846",
    "position": "Midfield - Attacking Midfield",
    "height": "1,83 m",
    "nation": "Germany",
    "nation_code": "de",
    "profile_url": "https://www.transfermarkt.us/robert-leipertz/profil/spieler/119120",
    "image_url": "https://img.a.transfermarkt.technology/portrait/big/119120-1719302586.jpg?lm=1",
    "club_logo_url": null,
    "date_of_birth": "01.02.1993",
    "place_of_birth": "Jülich",
    "status": "SSV Ulm 1846"
  },
  {
    "rank": 10,
    "name": "Florian Niederlechner",
    "full_name": "Unknown",
    "appearances": 84,
    "goals": 30,
    "assists": 14,
    "minutes_played": 5849,
    "period": "2013-2015",
    "jersey_name": "Niederlechner",
    "jersey_number": "Unknown",
    "yellow_cards": 12,
    "red_cards": 0,
    "club": "1.FC Heidenheim 1846",
    "position": "Attack - Centre-Forward",
    "height": "1,87 m",
    "nation": "Germany",
    "nation_code": "de",
    "profile_url": "https://www.transfermarkt.us/florian-niederlechner/profil/spieler/152963",
    "image_url": "https://img.a.transfermarkt.technology/portrait/big/152963-1720778535.jpg?lm=1",
    "club_logo_url": null,
    "date_of_birth": "24.10.1990",
    "place_of_birth": "Ebersberg",
    "status": "Hertha BSC"
  },
  {
    "rank": 11,
    "name": "Denis Thomalla",
    "full_name": "Unknown",
    "appearances": 211,
    "goals": 30,
    "assists": 21,
    "minutes_played": 12396,
    "period": "2016-2025",
    "jersey_name": "Thomalla",
    "jersey_number": "-",
    "yellow_cards": 7,
    "red_cards": 1,
    "club": "1.FC Heidenheim 1846",
    "position": "Midfield - Attacking Midfield",
    "height": "1,86 m",
    "nation": "Germany",
    "nation_code": "de",
    "profile_url": "https://www.transfermarkt.us/denis-thomalla/profil/spieler/94030",
    "image_url": "https://img.a.transfermarkt.technology/portrait/big/94030-1657875455.jpg?lm=1",
    "club_logo_url": null,
    "date_of_birth": "16.08.1992",
    "place_of_birth": "Pforzheim",
    "status": "AEL Limassol"
  },
  {
    "rank": 12,
    "name": "Alper Bagceci",
    "full_name": "Unknown",
    "appearances": 269,
    "goals": 26,
    "assists": 8,
    "minutes_played": 16324,
    "period": "2006-2015",
    "jersey_name": "Bagceci",
    "jersey_number": "Unknown",
    "yellow_cards": 41,
    "red_cards": 0,
    "club": "1.FC Heidenheim 1846",
    "position": "Midfield - Right Midfield",
    "height": "1,80 m",
    "nation": "Germany",
    "nation_code": "de",
    "profile_url": "https://www.transfermarkt.us/alper-bagceci/profil/spieler/11061",
    "image_url": "https://img.a.transfermarkt.technology/portrait/big/11061-1557159436.jpg?lm=1",
    "club_logo_url": null,
    "date_of_birth": "16.04.1984",
    "place_of_birth": "Ulm",
    "status": "Türkspor Neu-Ulm"
  },
  {
    "rank": 13,
    "name": "Bastian Heidenfelder",
    "full_name": "Unknown",
    "appearances": 119,
    "goals": 24,
    "assists": 9,
    "minutes_played": 6241,
    "period": "2009-2013",
    "jersey_name": "Heidenfelder",
    "jersey_number": "Unknown",
    "yellow_cards": 11,
    "red_cards": 0,
    "club": "1.FC Heidenheim 1846",
    "position": "Attack - Centre-Forward",
    "height": "1,74 m",
    "nation": "Germany",
    "nation_code": "de",
    "profile_url": "https://www.transfermarkt.us/bastian-heidenfelder/profil/spieler/15530",
    "image_url": "https://img.a.transfermarkt.technology/portrait/big/s_15530_2036_2010_2.jpg?lm=1",
    "club_logo_url": null,
    "date_of_birth": "08.01.1986",
    "place_of_birth": "Ansbach",
    "status": "Retired"
  },
  {
    "rank": 14,
    "name": "Robert Glatzel",
    "full_name": "Robert Nesta Glatzel",
    "appearances": 61,
    "goals": 24,
    "assists": 10,
    "minutes_played": 3949,
    "period": "2017-2019",
    "jersey_name": "Glatzel",
    "jersey_number": "Unknown",
    "yellow_cards": 6,
    "red_cards": 1,
    "club": "1.FC Heidenheim 1846",
    "position": "Attack - Centre-Forward",
    "height": "1,93 m",
    "nation": "Germany",
    "nation_code": "de",
    "profile_url": "https://www.transfermarkt.us/robert-glatzel/profil/spieler/196139",
    "image_url": "https://img.a.transfermarkt.technology/portrait/big/196139-1728397946.jpg?lm=1",
    "club_logo_url": null,
    "date_of_birth": "08.01.1994",
    "place_of_birth": "München",
    "status": "Hamburger SV"
  },
  {
    "rank": 15,
    "name": "Nikola Dovedan",
    "full_name": "Unknown",
    "appearances": 85,
    "goals": 20,
    "assists": 12,
    "minutes_played": 4991,
    "period": "17/19-23/24",
    "jersey_name": "Dovedan",
    "jersey_number": "-",
    "yellow_cards": 11,
    "red_cards": 1,
    "club": "1.FC Heidenheim 1846",
    "position": "Attack - Second Striker",
    "height": "1,72 m",
    "nation": "Austria",
    "nation_code": "at",
    "profile_url": "https://www.transfermarkt.us/nikola-dovedan/profil/spieler/120189",
    "image_url": "https://img.a.transfermarkt.technology/portrait/big/120189-1690187018.jpg?lm=1",
    "club_logo_url": null,
    "date_of_birth": "06.07.1994",
    "place_of_birth": "Tulln",
    "status": "Fatih Karagümrük"
  },
  {
    "rank": 16,
    "name": "Niklas Beste",
    "full_name": "Jan-Niklas Beste",
    "appearances": 68,
    "goals": 20,
    "assists": 28,
    "minutes_played": 5631,
    "period": "2022-2024",
    "jersey_name": "Beste",
    "jersey_number": "-",
    "yellow_cards": 8,
    "red_cards": 0,
    "club": "1.FC Heidenheim 1846",
    "position": "Attack - Left Winger",
    "height": "1,75 m",
    "nation": "Germany",
    "nation_code": "de",
    "profile_url": "https://www.transfermarkt.us/niklas-beste/profil/spieler/342967",
    "image_url": "https://img.a.transfermarkt.technology/portrait/big/342967-1690186107.jpg?lm=1",
    "club_logo_url": null,
    "date_of_birth": "04.01.1999",
    "place_of_birth": "Hamm",
    "status": "SC Freiburg"
  },
  {
    "rank": 17,
    "name": "Ertac Seskir",
    "full_name": "Unknown",
    "appearances": 138,
    "goals": 19,
    "assists": 1,
    "minutes_played": 10506,
    "period": "2003-2010",
    "jersey_name": "Seskir",
    "jersey_number": "Unknown",
    "yellow_cards": 20,
    "red_cards": 0,
    "club": "1.FC Heidenheim 1846",
    "position": "Midfield - Defensive Midfield",
    "height": "1,75 m",
    "nation": "Türkiye",
    "nation_code": "tr",
    "profile_url": "https://www.transfermarkt.us/ertac-seskir/profil/spieler/24761",
    "image_url": "https://img.a.transfermarkt.technology/portrait/big/f_B_s_24761_2036_2009_1.jpg?lm=1",
    "club_logo_url": null,
    "date_of_birth": "12.11.1982",
    "place_of_birth": "Schwäbisch Gmünd",
    "status": "TV Straßdorf"
  },
  {
    "rank": 18,
    "name": "Frank Schmidt",
    "full_name": "Unknown",
    "appearances": 88,
    "goals": 19,
    "assists": 0,
    "minutes_played": 7430,
    "period": "2003-2007",
    "jersey_name": "Schmidt",
    "jersey_number": "-",
    "yellow_cards": 19,
    "red_cards": 0,
    "club": "1.FC Heidenheim 1846",
    "position": "Midfield - Defensive Midfield",
    "height": "1,90 m",
    "nation": "Germany",
    "nation_code": "de",
    "profile_url": "https://www.transfermarkt.us/frank-schmidt/profil/spieler/926",
    "image_url": "https://img.a.transfermarkt.technology/portrait/big/926-1646044563.jpg?lm=1",
    "club_logo_url": null,
    "date_of_birth": "03.01.1974",
    "place_of_birth": "Heidenheim an der Brenz",
    "status": "Retired"
  },
  {
    "rank": 19,
    "name": "Patrick Mainka",
    "full_name": "Unknown",
    "appearances": 248,
    "goals": 19,
    "assists": 7,
    "minutes_played": 22227,
    "period": "2018-2025",
    "jersey_name": "Mainka",
    "jersey_number": "Unknown",
    "yellow_cards": 21,
    "red_cards": 0,
    "club": "1.FC Heidenheim 1846",
    "position": "Defender - Centre-Back",
    "height": "1,94 m",
    "nation": "Germany",
    "nation_code": "de",
    "profile_url": "https://www.transfermarkt.us/patrick-mainka/profil/spieler/133731",
    "image_url": "https://img.a.transfermarkt.technology/portrait/big/133731-1657874688.jpg?lm=1",
    "club_logo_url": null,
    "date_of_birth": "06.11.1994",
    "place_of_birth": "Gütersloh",
    "status": "1.FC Heidenheim 1846"
  },
  {
    "rank": 20,
    "name": "Christian Kühlwetter",
    "full_name": "Unknown",
    "appearances": 93,
    "goals": 18,
    "assists": 11,
    "minutes_played": 4985,
    "period": "2020-2024",
    "jersey_name": "Kühlwetter",
    "jersey_number": "Unknown",
    "yellow_cards": 13,
    "red_cards": 0,
    "club": "1.FC Heidenheim 1846",
    "position": "Attack - Centre-Forward",
    "height": "1,82 m",
    "nation": "Germany",
    "nation_code": "de",
    "profile_url": "https://www.transfermarkt.us/christian-kuhlwetter/profil/spieler/184204",
    "image_url": "https://img.a.transfermarkt.technology/portrait/big/184204-1690186941.jpg?lm=1",
    "club_logo_url": null,
    "date_of_birth": "21.04.1996",
    "place_of_birth": "Bonn",
    "status": "SSV Jahn Regensburg"
  },
  {
    "rank": 21,
    "name": "Stefan Schimmer",
    "full_name": "Unknown",
    "appearances": 149,
    "goals": 17,
    "assists": 12,
    "minutes_played": 3775,
    "period": "2019-2025",
    "jersey_name": "Schimmer",
    "jersey_number": "Unknown",
    "yellow_cards": 3,
    "red_cards": 0,
    "club": "1.FC Heidenheim 1846",
    "position": "Attack - Centre-Forward",
    "height": "1,85 m",
    "nation": "Germany",
    "nation_code": "de",
    "profile_url": "https://www.transfermarkt.us/stefan-schimmer/profil/spieler/394033",
    "image_url": "https://img.a.transfermarkt.technology/portrait/big/394033-1721852150.jpg?lm=1",
    "club_logo_url": null,
    "date_of_birth": "28.04.1994",
    "place_of_birth": "Wertingen",
    "status": "1.FC Heidenheim 1846"
  },
  {
    "rank": 22,
    "name": "Smail Morabit",
    "full_name": "Unknown",
    "appearances": 94,
    "goals": 17,
    "assists": 7,
    "minutes_played": 5993,
    "period": "2013-2017",
    "jersey_name": "Morabit",
    "jersey_number": "Unknown",
    "yellow_cards": 12,
    "red_cards": 0,
    "club": "1.FC Heidenheim 1846",
    "position": "Attack - Second Striker",
    "height": "1,78 m",
    "nation": "France",
    "nation_code": "fr",
    "profile_url": "https://www.transfermarkt.us/smail-morabit/profil/spieler/56502",
    "image_url": "https://img.a.transfermarkt.technology/portrait/big/56502-1660896817.png?lm=1",
    "club_logo_url": null,
    "date_of_birth": "05.07.1988",
    "place_of_birth": "Forbach",
    "status": "SSEP Hombourg-Haut"
  },
  {
    "rank": 23,
    "name": "John Verhoek",
    "full_name": "Unknown",
    "appearances": 57,
    "goals": 16,
    "assists": 5,
    "minutes_played": 4048,
    "period": "2016-2018",
    "jersey_name": "Verhoek",
    "jersey_number": "Unknown",
    "yellow_cards": 5,
    "red_cards": 0,
    "club": "1.FC Heidenheim 1846",
    "position": "Attack - Centre-Forward",
    "height": "1,88 m",
    "nation": "Netherlands",
    "nation_code": "nl",
    "profile_url": "https://www.transfermarkt.us/john-verhoek/profil/spieler/75295",
    "image_url": "https://img.a.transfermarkt.technology/portrait/big/75295-1698436410.JPG?lm=1",
    "club_logo_url": null,
    "date_of_birth": "25.03.1989",
    "place_of_birth": "Leidschendam",
    "status": "De Tubanters 1897"
  },
  {
    "rank": 24,
    "name": "Christian Gmünder",
    "full_name": "Unknown",
    "appearances": 81,
    "goals": 14,
    "assists": 1,
    "minutes_played": 5944,
    "period": "2006-2010",
    "jersey_name": "Gmünder",
    "jersey_number": "Unknown",
    "yellow_cards": 17,
    "red_cards": 0,
    "club": "1.FC Heidenheim 1846",
    "position": "Midfield - Left Midfield",
    "height": "1,77 m",
    "nation": "Germany",
    "nation_code": "de",
    "profile_url": "https://www.transfermarkt.us/christian-gmunder/profil/spieler/5038",
    "image_url": "https://img.a.transfermarkt.technology/portrait/big/U_K_s_5038_2036_2009_1.jpg?lm=1",
    "club_logo_url": null,
    "date_of_birth": "12.02.1980",
    "place_of_birth": "Leutkirch im Allgäu",
    "status": "Retired"
  },
  {
    "rank": 25,
    "name": "Michael Thurk",
    "full_name": "Unknown",
    "appearances": 71,
    "goals": 14,
    "assists": 11,
    "minutes_played": 3955,
    "period": "2012-2014",
    "jersey_name": "Thurk",
    "jersey_number": "-",
    "yellow_cards": 5,
    "red_cards": 2,
    "club": "1.FC Heidenheim 1846",
    "position": "Attack - Centre-Forward",
    "height": "1,78 m",
    "nation": "Germany",
    "nation_code": "de",
    "profile_url": "https://www.transfermarkt.us/michael-thurk/profil/spieler/1077",
    "image_url": "https://img.a.transfermarkt.technology/portrait/big/1077-1599466953.jpg?lm=1",
    "club_logo_url": null,
    "date_of_birth": "28.05.1976",
    "place_of_birth": "Frankfurt am Main",
    "status": "Retired"
  },
  {
    "rank": 26,
    "name": "Richard Weil",
    "full_name": "Unknown",
    "appearances": 98,
    "goals": 13,
    "assists": 22,
    "minutes_played": 7641,
    "period": "2009-2013",
    "jersey_name": "Weil",
    "jersey_number": "Unknown",
    "yellow_cards": 8,
    "red_cards": 0,
    "club": "1.FC Heidenheim 1846",
    "position": "Midfield - Defensive Midfield",
    "height": "1,83 m",
    "nation": "Germany",
    "nation_code": "de",
    "profile_url": "https://www.transfermarkt.us/richard-weil/profil/spieler/49032",
    "image_url": "https://img.a.transfermarkt.technology/portrait/big/49032-1629993203.jpg?lm=1",
    "club_logo_url": null,
    "date_of_birth": "06.02.1988",
    "place_of_birth": "Frankfurt am Main",
    "status": "FSV Fernwald"
  },
  {
    "rank": 27,
    "name": "Marvin Pieringer",
    "full_name": "Unknown",
    "appearances": 64,
    "goals": 13,
    "assists": 7,
    "minutes_played": 3634,
    "period": "2023-2025",
    "jersey_name": "Pieringer",
    "jersey_number": "Unknown",
    "yellow_cards": 13,
    "red_cards": 0,
    "club": "1.FC Heidenheim 1846",
    "position": "Attack - Centre-Forward",
    "height": "1,91 m",
    "nation": "Germany",
    "nation_code": "de",
    "profile_url": "https://www.transfermarkt.us/marvin-pieringer/profil/spieler/471055",
    "image_url": "https://img.a.transfermarkt.technology/portrait/big/471055-1690186870.jpg?lm=1",
    "club_logo_url": null,
    "date_of_birth": "04.10.1999",
    "place_of_birth": "Bad Urach",
    "status": "1.FC Heidenheim 1846"
  },
  {
    "rank": 28,
    "name": "Arne Feick",
    "full_name": "Unknown",
    "appearances": 127,
    "goals": 12,
    "assists": 15,
    "minutes_played": 10575,
    "period": "2015-2020",
    "jersey_name": "Feick",
    "jersey_number": "11",
    "yellow_cards": 19,
    "red_cards": 0,
    "club": "1.FC Heidenheim 1846",
    "position": "Defender - Left-Back",
    "height": null,
    "nation": "Germany",
    "nation_code": "de",
    "profile_url": "https://www.transfermarkt.us/arne-feick/profil/spieler/38609",
    "image_url": "https://img.a.transfermarkt.technology/portrait/big/38609-1617109751.jpg?lm=1",
    "club_logo_url": null,
    "date_of_birth": "01.04.1988",
    "place_of_birth": "Berlin",
    "status": "Retired"
  },
  {
    "rank": 29,
    "name": "Christian Essig",
    "full_name": "Unknown",
    "appearances": 82,
    "goals": 11,
    "assists": 10,
    "minutes_played": 4740,
    "period": "2008-2012",
    "jersey_name": "Essig",
    "jersey_number": "Unknown",
    "yellow_cards": 14,
    "red_cards": 0,
    "club": "1.FC Heidenheim 1846",
    "position": "Midfield - Right Midfield",
    "height": "1,80 m",
    "nation": "Germany",
    "nation_code": "de",
    "profile_url": "https://www.transfermarkt.us/christian-essig/profil/spieler/31691",
    "image_url": "https://img.a.transfermarkt.technology/portrait/big/s_31691_2036_2010_2.jpg?lm=1",
    "club_logo_url": null,
    "date_of_birth": "24.01.1986",
    "place_of_birth": "Rastatt",
    "status": "FV 08 Unterkochen"
  },
  {
    "rank": 30,
    "name": "Tobias Mohr",
    "full_name": "Unknown",
    "appearances": 78,
    "goals": 11,
    "assists": 17,
    "minutes_played": 4667,
    "period": "2020-2022",
    "jersey_name": "Mohr",
    "jersey_number": "Unknown",
    "yellow_cards": 4,
    "red_cards": 0,
    "club": "1.FC Heidenheim 1846",
    "position": "Midfield - Left Midfield",
    "height": "1,82 m",
    "nation": "Germany",
    "nation_code": "de",
    "profile_url": "https://www.transfermarkt.us/tobias-mohr/profil/spieler/153661",
    "image_url": "https://img.a.transfermarkt.technology/portrait/big/153661-1657108199.jpg?lm=1",
    "club_logo_url": null,
    "date_of_birth": "24.08.1995",
    "place_of_birth": "Aachen",
    "status": "FC Schalke 04"
  }
]