[
  {
      "rank": 1,
      "name": "Rubén Castro",
      "full_name": "Rubén Castro Martín",
      "appearances": 289,
      "goals": 148,
      "assists": 36,
      "minutes_played": 23772,
      "period": "10/16-17/18",
      "jersey_name": "Castro",
      "jersey_number": "Unknown",
      "yellow_cards": 23,
      "red_cards": 0,
      "club": "Real Betis Balompié",
      "position": "Attack - Centre-Forward",
      "height": "1,69 m",
      "nation": "Spain",
      "nation_code": "es",
      "profile_url": "https://www.transfermarkt.us/ruben-castro/profil/spieler/25316",
      "image_url": "https://img.a.transfermarkt.technology/portrait/big/25316-1638441797.jpg?lm=1",
      "club_logo_url": null,
      "date_of_birth": "27.06.1981",
      "place_of_birth": "Las Palmas de Gran Canaria",
      "status": "Retired"
  },
  {
      "rank": 2,
      "name": "Poli Rincón",
      "full_name": "Hipólito Rincón Povedano",
      "appearances": 238,
      "goals": 83,
      "assists": 1,
      "minutes_played": 18478,
      "period": "1981-1990",
      "jersey_name": "Rincón",
      "jersey_number": "Unknown",
      "yellow_cards": 31,
      "red_cards": 5,
      "club": "Real Betis Balompié",
      "position": "Attack - Centre-Forward",
      "height": "1,80 m",
      "nation": "Spain",
      "nation_code": "es",
      "profile_url": "https://www.transfermarkt.us/poli-rincon/profil/spieler/117608",
      "image_url": "https://www.bdfutbol.com/i/j/2942c.jpg",
      "club_logo_url": null,
      "date_of_birth": "28.04.1957",
      "place_of_birth": "Madrid",
      "status": "Retired"
  },
  {
      "rank": 3,
      "name": "Alfonso",
      "full_name": "Alfonso Pérez Muñoz",
      "appearances": 228,
      "goals": 80,
      "assists": 7,
      "minutes_played": 17768,
      "period": "95/00-02/05",
      "jersey_name": "Alfonso",
      "jersey_number": "Unknown",
      "yellow_cards": 39,
      "red_cards": 1,
      "club": "Real Betis Balompié",
      "position": "Attack - Centre-Forward",
      "height": "1,78 m",
      "nation": "Spain",
      "nation_code": "es",
      "profile_url": "https://www.transfermarkt.us/alfonso/profil/spieler/7933",
      "image_url": "https://img.a.transfermarkt.technology/portrait/big/7933-1492517153.jpg?lm=1",
      "club_logo_url": null,
      "date_of_birth": "26.09.1972",
      "place_of_birth": "Getafe",
      "status": "Retired"
  },
  {
      "rank": 4,
      "name": "Jorge Molina",
      "full_name": "Jorge Molina Vidal",
      "appearances": 211,
      "goals": 77,
      "assists": 19,
      "minutes_played": 13364,
      "period": "2010-2016",
      "jersey_name": "Molina",
      "jersey_number": "Unknown",
      "yellow_cards": 25,
      "red_cards": 1,
      "club": "Real Betis Balompié",
      "position": "Attack - Centre-Forward",
      "height": "1,88 m",
      "nation": "Spain",
      "nation_code": "es",
      "profile_url": "https://www.transfermarkt.us/jorge-molina/profil/spieler/57825",
      "image_url": "https://img.a.transfermarkt.technology/portrait/big/57825-1447256894.jpg?lm=1",
      "club_logo_url": null,
      "date_of_birth": "22.04.1982",
      "place_of_birth": "Alcoy",
      "status": "Retired"
  },
  {
      "rank": 5,
      "name": "Joaquín",
      "full_name": "Unknown",
      "appearances": 498,
      "goals": 66,
      "assists": 68,
      "minutes_played": 33603,
      "period": "00/06-15/23",
      "jersey_name": "Joaquín",
      "jersey_number": "Unknown",
      "yellow_cards": 47,
      "red_cards": 2,
      "club": "Real Betis Balompié",
      "position": "Attack - Right Winger",
      "height": "1,81 m",
      "nation": "Spain",
      "nation_code": "es",
      "profile_url": "https://www.transfermarkt.us/joaquin/profil/spieler/7663",
      "image_url": "https://img.a.transfermarkt.technology/portrait/big/7663-1650864280.jpg?lm=1",
      "club_logo_url": null,
      "date_of_birth": "21.07.1981",
      "place_of_birth": "El Puerto de Santa María",
      "status": "Retired"
  },
  {
      "rank": 6,
      "name": "Fernando Ansola",
      "full_name": "Fernando Ansola San Martín",
      "appearances": 123,
      "goals": 61,
      "assists": 0,
      "minutes_played": 11070,
      "period": "1961-1966",
      "jersey_name": "Ansola",
      "jersey_number": "Unknown",
      "yellow_cards": 0,
      "red_cards": 0,
      "club": "Real Betis Balompié",
      "position": "Attack",
      "height": "1,80 m",
      "nation": "Spain",
      "nation_code": "es",
      "profile_url": "https://www.transfermarkt.us/fernando-ansola/profil/spieler/309020",
      "image_url": "https://www.bdfutbol.com/i/j/5718b.jpg",
      "club_logo_url": null,
      "date_of_birth": "27.01.1940",
      "place_of_birth": "Elgoibar",
      "status": "---"
  },
  {
      "rank": 7,
      "name": "Borja Iglesias",
      "full_name": "Borja Iglesias Quintas",
      "appearances": 181,
      "goals": 52,
      "assists": 12,
      "minutes_played": 9981,
      "period": "19/23-24/25",
      "jersey_name": "Iglesias",
      "jersey_number": "#7",
      "yellow_cards": 14,
      "red_cards": 2,
      "club": "Real Betis Balompié",
      "position": "Attack - Centre-Forward",
      "height": "1,87 m",
      "nation": "Spain",
      "nation_code": "es",
      "profile_url": "https://www.transfermarkt.us/borja-iglesias/profil/spieler/278359",
      "image_url": "https://img.a.transfermarkt.technology/portrait/big/278359-1686661509.jpg?lm=1",
      "club_logo_url": null,
      "date_of_birth": "17.01.1993",
      "place_of_birth": "Santiago de Compostela",
      "status": "Celta de Vigo"
  },
  {
      "rank": 8,
      "name": "Finidi George",
      "full_name": "Unknown",
      "appearances": 151,
      "goals": 44,
      "assists": 7,
      "minutes_played": 12884,
      "period": "1996-2000",
      "jersey_name": "George",
      "jersey_number": "Unknown",
      "yellow_cards": 18,
      "red_cards": 0,
      "club": "Real Betis Balompié",
      "position": "Attack - Right Winger",
      "height": "1,89 m",
      "nation": "Nigeria",
      "nation_code": "ng",
      "profile_url": "https://www.transfermarkt.us/finidi-george/profil/spieler/13241",
      "image_url": "https://img.a.transfermarkt.technology/portrait/big/13241-1447873328.jpg?lm=1",
      "club_logo_url": null,
      "date_of_birth": "15.04.1971",
      "place_of_birth": "Port Harcourt",
      "status": "Retired"
  },
  {
      "rank": 9,
      "name": "Gabriel Calderón",
      "full_name": "Gabriel Humberto Calderón Metralla",
      "appearances": 151,
      "goals": 43,
      "assists": 1,
      "minutes_played": 12976,
      "period": "1983-1987",
      "jersey_name": "Calderón",
      "jersey_number": "Unknown",
      "yellow_cards": 12,
      "red_cards": 1,
      "club": "Real Betis Balompié",
      "position": "Attack - Left Winger",
      "height": "1,80 m",
      "nation": "Argentina",
      "nation_code": "ar",
      "profile_url": "https://www.transfermarkt.us/gabriel-calderon/profil/spieler/106973",
      "image_url": "https://img.a.transfermarkt.technology/portrait/big/106973-1630586947.jpg?lm=1",
      "club_logo_url": null,
      "date_of_birth": "07.02.1960",
      "place_of_birth": "Rawson",
      "status": "Retired"
  },
  {
      "rank": 10,
      "name": "Julio Cardeñosa",
      "full_name": "Julio Cardeñosa Rodríguez",
      "appearances": 338,
      "goals": 41,
      "assists": 0,
      "minutes_played": 28673,
      "period": "1974-1985",
      "jersey_name": "Cardeñosa",
      "jersey_number": "Unknown",
      "yellow_cards": 11,
      "red_cards": 1,
      "club": "Real Betis Balompié",
      "position": "Midfield - Left Midfield",
      "height": null,
      "nation": "Spain",
      "nation_code": "es",
      "profile_url": "https://www.transfermarkt.us/julio-cardenosa/profil/spieler/135093",
      "image_url": "https://www.bdfutbol.com/i/j/3515.jpg",
      "club_logo_url": null,
      "date_of_birth": "27.10.1949",
      "place_of_birth": "Valladolid",
      "status": "Retired"
  },
  {
      "rank": 11,
      "name": "Edú",
      "full_name": "Unknown",
      "appearances": 155,
      "goals": 39,
      "assists": 9,
      "minutes_played": 12491,
      "period": "2004-2009",
      "jersey_name": "Edú",
      "jersey_number": "Unknown",
      "yellow_cards": 19,
      "red_cards": 2,
      "club": "Real Betis Balompié",
      "position": "Attack - Second Striker",
      "height": "1,82 m",
      "nation": "Brazil",
      "nation_code": "br",
      "profile_url": "https://www.transfermarkt.us/edutm/profil/spieler/7550",
      "image_url": "https://img.a.transfermarkt.technology/portrait/big/7550-1706641950.jpg?lm=1",
      "club_logo_url": null,
      "date_of_birth": "10.01.1979",
      "place_of_birth": "Jaú",
      "status": "Retired"
  },
  {
      "rank": 12,
      "name": "Rogelio Sosa",
      "full_name": "Rogelio Sosa Ramírez",
      "appearances": 183,
      "goals": 39,
      "assists": 0,
      "minutes_played": 14516,
      "period": "1962-1978",
      "jersey_name": "Sosa",
      "jersey_number": "Unknown",
      "yellow_cards": 3,
      "red_cards": 2,
      "club": "Real Betis Balompié",
      "position": "Midfield - Attacking Midfield",
      "height": "Unknown",
      "nation": "Spain",
      "nation_code": "es",
      "profile_url": "https://www.transfermarkt.us/rogelio-sosa/profil/spieler/342626",
      "image_url": "https://www.bdfutbol.com/i/j/5303.jpg",
      "club_logo_url": null,
      "date_of_birth": "11.04.1943",
      "place_of_birth": "Coria del Río",
      "status": "---"
  },
  {
      "rank": 13,
      "name": "Sergio Canales",
      "full_name": "Sergio Canales Madrazo",
      "appearances": 207,
      "goals": 39,
      "assists": 30,
      "minutes_played": 16761,
      "period": "2018-2023",
      "jersey_name": "Canales",
      "jersey_number": "#10",
      "yellow_cards": 26,
      "red_cards": 1,
      "club": "Real Betis Balompié",
      "position": "Midfield - Attacking Midfield",
      "height": "1,78 m",
      "nation": "Spain",
      "nation_code": "es",
      "profile_url": "https://www.transfermarkt.us/sergio-canales/profil/spieler/66106",
      "image_url": "https://img.a.transfermarkt.technology/portrait/big/66106-1653039158.jpg?lm=1",
      "club_logo_url": null,
      "date_of_birth": "16.02.1991",
      "place_of_birth": "Santander",
      "status": "CF Monterrey"
  },
  {
      "rank": 14,
      "name": "Ricardo Oliveira",
      "full_name": "Unknown",
      "appearances": 74,
      "goals": 37,
      "assists": 4,
      "minutes_played": 6420,
      "period": "04/06-2009",
      "jersey_name": "Ricardo Oliveira",
      "jersey_number": "Unknown",
      "yellow_cards": 13,
      "red_cards": 1,
      "club": "Real Betis Balompié",
      "position": "Attack - Centre-Forward",
      "height": "1,83 m",
      "nation": "Brazil",
      "nation_code": "br",
      "profile_url": "https://www.transfermarkt.us/ricardo-oliveira/profil/spieler/15468",
      "image_url": "https://img.a.transfermarkt.technology/portrait/big/15468-1413446874.jpg?lm=1",
      "club_logo_url": null,
      "date_of_birth": "06.05.1980",
      "place_of_birth": "São Paulo",
      "status": "Retired"
  },
  {
      "rank": 15,
      "name": "Luis Aragonés",
      "full_name": "José Luis Aragonés Suárez Martínez",
      "appearances": 89,
      "goals": 36,
      "assists": 0,
      "minutes_played": 7988,
      "period": "1961-1964",
      "jersey_name": "Aragonés",
      "jersey_number": "Unknown",
      "yellow_cards": 0,
      "red_cards": 1,
      "club": "Real Betis Balompié",
      "position": "Midfield - Central Midfield",
      "height": null,
      "nation": "Spain",
      "nation_code": "es",
      "profile_url": "https://www.transfermarkt.us/luis-aragones/profil/spieler/135744",
      "image_url": "https://img.a.transfermarkt.technology/portrait/big/135744-1476196738.jpg?lm=1",
      "club_logo_url": null,
      "date_of_birth": "28.07.1938",
      "place_of_birth": "Madrid",
      "status": "---"
  },
  {
      "rank": 16,
      "name": "Achille Emaná",
      "full_name": "Achille Emaná Edzimbi",
      "appearances": 100,
      "goals": 36,
      "assists": 7,
      "minutes_played": 7678,
      "period": "2008-2011",
      "jersey_name": "Emaná",
      "jersey_number": "Unknown",
      "yellow_cards": 18,
      "red_cards": 1,
      "club": "Real Betis Balompié",
      "position": "Midfield - Attacking Midfield",
      "height": "1,80 m",
      "nation": "Cameroon",
      "nation_code": "cm",
      "profile_url": "https://www.transfermarkt.us/achille-emana/profil/spieler/7020",
      "image_url": "https://img.a.transfermarkt.technology/portrait/big/s_7020_3711_2013_11_15_1.jpg?lm=1",
      "club_logo_url": null,
      "date_of_birth": "05.06.1982",
      "place_of_birth": "Bipindi",
      "status": "Retired"
  },
  {
      "rank": 17,
      "name": "Lobo Diarte",
      "full_name": "Carlos Martínez Diarte",
      "appearances": 83,
      "goals": 33,
      "assists": 1,
      "minutes_played": 7312,
      "period": "1980-1983",
      "jersey_name": "Diarte",
      "jersey_number": "Unknown",
      "yellow_cards": 9,
      "red_cards": 1,
      "club": "Real Betis Balompié",
      "position": "Attack - Centre-Forward",
      "height": null,
      "nation": "Paraguay",
      "nation_code": "py",
      "profile_url": "https://www.transfermarkt.us/lobo-diarte/profil/spieler/172004",
      "image_url": "https://www.bdfutbol.com/i/j/3736.jpg",
      "club_logo_url": null,
      "date_of_birth": "26.01.1954",
      "place_of_birth": "Asunción",
      "status": "---"
  },
  {
      "rank": 18,
      "name": "Fernando",
      "full_name": "Fernando Miguel Fernández Escribano",
      "appearances": 187,
      "goals": 32,
      "assists": 7,
      "minutes_played": 11440,
      "period": "2002-2008",
      "jersey_name": "Fernando",
      "jersey_number": "Unknown",
      "yellow_cards": 15,
      "red_cards": 0,
      "club": "Real Betis Balompié",
      "position": "Midfield - Attacking Midfield",
      "height": "1,81 m",
      "nation": "Spain",
      "nation_code": "es",
      "profile_url": "https://www.transfermarkt.us/fernando/profil/spieler/15721",
      "image_url": "https://img.a.transfermarkt.technology/portrait/big/s_15721_9241_2010_1.jpg?lm=1",
      "club_logo_url": null,
      "date_of_birth": "02.06.1979",
      "place_of_birth": "Málaga",
      "status": "Retired"
  },
  {
      "rank": 19,
      "name": "Javier López",
      "full_name": "Francisco Javier López García",
      "appearances": 286,
      "goals": 31,
      "assists": 0,
      "minutes_played": 23734,
      "period": "1970-1982",
      "jersey_name": "López",
      "jersey_number": "Unknown",
      "yellow_cards": 26,
      "red_cards": 1,
      "club": "Real Betis Balompié",
      "position": "Midfield",
      "height": "1,74 m",
      "nation": "Spain",
      "nation_code": "es",
      "profile_url": "https://www.transfermarkt.us/javier-lopez/profil/spieler/366112",
      "image_url": "https://www.bdfutbol.com/i/j/3880d.jpg",
      "club_logo_url": null,
      "date_of_birth": "14.10.1950",
      "place_of_birth": "Laredo",
      "status": "Retired"
  },
  {
      "rank": 20,
      "name": "Victorio Unamuno",
      "full_name": "Victorio Unamuno Ibarzabal",
      "appearances": 59,
      "goals": 31,
      "assists": 0,
      "minutes_played": 5305,
      "period": "1933-1936",
      "jersey_name": "Unamuno",
      "jersey_number": "Unknown",
      "yellow_cards": 0,
      "red_cards": 0,
      "club": "Real Betis Balompié",
      "position": "Attack",
      "height": "Unknown",
      "nation": "Spain",
      "nation_code": "es",
      "profile_url": "https://www.transfermarkt.us/victorio-unamuno/profil/spieler/135776",
      "image_url": "https://www.bdfutbol.com/i/j/11020b.jpg",
      "club_logo_url": null,
      "date_of_birth": "21.05.1909",
      "place_of_birth": "Bergara",
      "status": "---"
  },
  {
      "rank": 21,
      "name": "Juanmi",
      "full_name": "Unknown",
      "appearances": 120,
      "goals": 31,
      "assists": 7,
      "minutes_played": 5796,
      "period": "19/24-2025",
      "jersey_name": "Juanmi",
      "jersey_number": "#24",
      "yellow_cards": 13,
      "red_cards": 0,
      "club": "Real Betis Balompié",
      "position": "Attack - Left Winger",
      "height": "1,72 m",
      "nation": "Spain",
      "nation_code": "es",
      "profile_url": "https://www.transfermarkt.us/juanmi/profil/spieler/126737",
      "image_url": "https://img.a.transfermarkt.technology/portrait/big/126737-1653043231.jpg?lm=1",
      "club_logo_url": null,
      "date_of_birth": "20.05.1993",
      "place_of_birth": "Coín",
      "status": "Getafe CF"
  },
  {
      "rank": 22,
      "name": "Willian José",
      "full_name": "Unknown",
      "appearances": 126,
      "goals": 31,
      "assists": 12,
      "minutes_played": 5985,
      "period": "2021-22/24",
      "jersey_name": "Willian José",
      "jersey_number": "#12",
      "yellow_cards": 4,
      "red_cards": 1,
      "club": "Real Betis Balompié",
      "position": "Attack - Centre-Forward",
      "height": "1,86 m",
      "nation": "Brazil",
      "nation_code": "br",
      "profile_url": "https://www.transfermarkt.us/willian-jose/profil/spieler/122155",
      "image_url": "https://img.a.transfermarkt.technology/portrait/big/122155-1720075360.png?lm=1",
      "club_logo_url": null,
      "date_of_birth": "23.11.1991",
      "place_of_birth": "Porto Calvo",
      "status": "Esporte Clube Bahia"
  },
  {
      "rank": 23,
      "name": "Enrique Morán",
      "full_name": "Enrique Morán Blanco",
      "appearances": 67,
      "goals": 31,
      "assists": 0,
      "minutes_played": 5835,
      "period": "1979-1981",
      "jersey_name": "Morán",
      "jersey_number": "Unknown",
      "yellow_cards": 1,
      "red_cards": 0,
      "club": "Real Betis Balompié",
      "position": "Attack - Centre-Forward",
      "height": "1,77 m",
      "nation": "Spain",
      "nation_code": "es",
      "profile_url": "https://www.transfermarkt.us/enrique-moran/profil/spieler/214140",
      "image_url": "https://www.bdfutbol.com/i/j/3374c.jpg",
      "club_logo_url": null,
      "date_of_birth": "15.10.1953",
      "place_of_birth": "Pola de Lena",
      "status": "Retired"
  },
  {
      "rank": 24,
      "name": "Ángel Cuéllar",
      "full_name": "Angel Manuel Cuéllar Llanos",
      "appearances": 153,
      "goals": 30,
      "assists": 0,
      "minutes_played": 9513,
      "period": "90/95-97/01",
      "jersey_name": "Cuéllar",
      "jersey_number": "Unknown",
      "yellow_cards": 19,
      "red_cards": 2,
      "club": "Real Betis Balompié",
      "position": "Attack - Left Winger",
      "height": null,
      "nation": "Spain",
      "nation_code": "es",
      "profile_url": "https://www.transfermarkt.us/angel-cuellar/profil/spieler/8066",
      "image_url": "https://www.bdfutbol.com/i/j/189.jpg",
      "club_logo_url": null,
      "date_of_birth": "13.09.1972",
      "place_of_birth": "Villafranca de los Barros",
      "status": "Retired"
  },
  {
      "rank": 25,
      "name": "Eduardo Anzarda",
      "full_name": "Eduardo Anzarda Álvarez",
      "appearances": 101,
      "goals": 30,
      "assists": 0,
      "minutes_played": 7228,
      "period": "1973-1980",
      "jersey_name": "Anzarda",
      "jersey_number": "Unknown",
      "yellow_cards": 4,
      "red_cards": 0,
      "club": "Real Betis Balompié",
      "position": "Attack",
      "height": "Unknown",
      "nation": "Argentina",
      "nation_code": "ar",
      "profile_url": "https://www.transfermarkt.us/eduardo-anzarda/profil/spieler/305402",
      "image_url": "https://www.bdfutbol.com/i/j/5117.jpg",
      "club_logo_url": null,
      "date_of_birth": "25.01.1944",
      "place_of_birth": "Buenos Aires",
      "status": "Retired"
  },
  {
      "rank": 26,
      "name": "Nabil Fekir",
      "full_name": "نبيل فقير",
      "appearances": 165,
      "goals": 29,
      "assists": 29,
      "minutes_played": 12293,
      "period": "2019-2024",
      "jersey_name": "Fekir",
      "jersey_number": "#20",
      "yellow_cards": 26,
      "red_cards": 4,
      "club": "Real Betis Balompié",
      "position": "Midfield - Attacking Midfield",
      "height": "1,73 m",
      "nation": "France",
      "nation_code": "fr",
      "profile_url": "https://www.transfermarkt.us/nabil-fekir/profil/spieler/203496",
      "image_url": "https://img.a.transfermarkt.technology/portrait/big/203496-1653041152.jpg?lm=1",
      "club_logo_url": null,
      "date_of_birth": "18.07.1993",
      "place_of_birth": "Lyon",
      "status": "Al-Jazira Club"
  },
  {
      "rank": 27,
      "name": "Loren Morón",
      "full_name": "Lorenzo Morón García",
      "appearances": 131,
      "goals": 29,
      "assists": 7,
      "minutes_played": 7080,
      "period": "18/22-2023",
      "jersey_name": "Morón",
      "jersey_number": "#80",
      "yellow_cards": 13,
      "red_cards": 1,
      "club": "Real Betis Balompié",
      "position": "Attack - Centre-Forward",
      "height": "1,85 m",
      "nation": "Spain",
      "nation_code": "es",
      "profile_url": "https://www.transfermarkt.us/loren-moron/profil/spieler/354741",
      "image_url": "https://img.a.transfermarkt.technology/portrait/big/354741-1709118089.jpeg?lm=1",
      "club_logo_url": null,
      "date_of_birth": "30.12.1993",
      "place_of_birth": "Marbella",
      "status": "Aris Thessaloniki"
  },
  {
      "rank": 28,
      "name": "Alexis Trujillo",
      "full_name": "Humberto Alexis Trujillo Oramas",
      "appearances": 249,
      "goals": 29,
      "assists": 2,
      "minutes_played": 19618,
      "period": "1993-2000",
      "jersey_name": "Trujillo",
      "jersey_number": "Unknown",
      "yellow_cards": 47,
      "red_cards": 0,
      "club": "Real Betis Balompié",
      "position": "Midfield - Central Midfield",
      "height": "1,74 m",
      "nation": "Spain",
      "nation_code": "es",
      "profile_url": "https://www.transfermarkt.us/alexis-trujillo/profil/spieler/253525",
      "image_url": "https://www.bdfutbol.com/i/j/1046d.jpg",
      "club_logo_url": null,
      "date_of_birth": "30.07.1965",
      "place_of_birth": "Las Palmas de Gran Canaria",
      "status": "Retired"
  },
  {
      "rank": 29,
      "name": "Joaquín Parra",
      "full_name": "Antonio Joaquín Parra Fernández",
      "appearances": 248,
      "goals": 28,
      "assists": 0,
      "minutes_played": 21164,
      "period": "1980-1987",
      "jersey_name": "Parra",
      "jersey_number": "Unknown",
      "yellow_cards": 6,
      "red_cards": 0,
      "club": "Real Betis Balompié",
      "position": "Midfield - Right Midfield",
      "height": "1,75 m",
      "nation": "Spain",
      "nation_code": "es",
      "profile_url": "https://www.transfermarkt.us/joaquin-parra/profil/spieler/180079",
      "image_url": "https://www.bdfutbol.com/i/j/257.jpg",
      "club_logo_url": null,
      "date_of_birth": "17.06.1961",
      "place_of_birth": "Sevilla",
      "status": "Retired"
  },
  {
      "rank": 30,
      "name": "Rafael Gordillo",
      "full_name": "Rafael Gordillo Vázquez",
      "appearances": 307,
      "goals": 26,
      "assists": 1,
      "minutes_played": 26579,
      "period": "76/85-92/95",
      "jersey_name": "Gordillo",
      "jersey_number": "Unknown",
      "yellow_cards": 9,
      "red_cards": 0,
      "club": "Real Betis Balompié",
      "position": "Defender - Left-Back",
      "height": "1,80 m",
      "nation": "Spain",
      "nation_code": "es",
      "profile_url": "https://www.transfermarkt.us/rafael-gordillo/profil/spieler/117603",
      "image_url": "https://img.a.transfermarkt.technology/portrait/big/117603-1538382026.jpg?lm=1",
      "club_logo_url": null,
      "date_of_birth": "24.02.1957",
      "place_of_birth": "Almendralejo",
      "status": "Retired"
  }
]